examples/basic.py
furthermore_py/__init__.py
furthermore_py/client.py
furthermore_py-0.1.3.dist-info/licenses/LICENSE
furthermore_py-0.1.3.dist-info/METADATA
furthermore_py-0.1.3.dist-info/WHEEL
furthermore_py-0.1.3.dist-info/top_level.txt
furthermore_py-0.1.3.dist-info/RECORD
