Metadata-Version: 2.4
Name: furthermore-py
Version: 0.1.3
Summary: Add your description here
Requires-Python: >=3.10
License-File: LICENSE
Requires-Dist: requests>=2.32.3
Dynamic: license-file
